pyembree/rtcore_scene.cpython-38-x86_64-linux-gnu.so
pyembree/mesh_construction.cpython-38-x86_64-linux-gnu.so
pyembree/rtcore.cpython-38-x86_64-linux-gnu.so
pyembree/_version.py
pyembree/triangles.cpython-38-x86_64-linux-gnu.so
pyembree/__init__.py
pyembree-0.2.11.dist-info/AUTHORS
pyembree-0.2.11.dist-info/WHEEL
pyembree-0.2.11.dist-info/top_level.txt
pyembree-0.2.11.dist-info/METADATA
pyembree-0.2.11.dist-info/RECORD
pyembree-0.2.11.dist-info/LICENSE
pyembree.libs/libtbb-1f9ff2d0.so.2
pyembree.libs/libtbbmalloc-ceb46550.so.2
pyembree.libs/libembree-4458e9e2.so.2
